viyv_mcp/__init__.py
viyv_mcp/_version.py
viyv_mcp/agent_runtime.py
viyv_mcp/cli.py
viyv_mcp/core.py
viyv_mcp/decorators.py
viyv_mcp/openai_bridge.py
viyv_mcp/run_context.py
viyv_mcp/app/__init__.py
viyv_mcp/app/bridge_manager.py
viyv_mcp/app/config.py
viyv_mcp/app/entry_registry.py
viyv_mcp/app/lifespan.py
viyv_mcp/app/logging_config.py
viyv_mcp/app/mcp_initialize_fix.py
viyv_mcp/app/registry.py
viyv_mcp/app/request_interceptor.py
viyv_mcp/app/adapters/slack_adapter.py
viyv_mcp/templates/Dockerfile
viyv_mcp/templates/main.py
viyv_mcp/templates/pyproject.toml
viyv_mcp/templates/app/config.py
viyv_mcp/templates/app/agents/sample_calc_agent.py
viyv_mcp/templates/app/agents/sample_notion_agent.py
viyv_mcp/templates/app/agents/sample_slack_agent.py
viyv_mcp/templates/app/agents/sample_slack_response_agent.py
viyv_mcp/templates/app/agents/sample_think_agent.py
viyv_mcp/templates/app/entries/sample_health.py
viyv_mcp/templates/app/entries/sample_slack.py
viyv_mcp/templates/app/entries/sample_webhook.py
viyv_mcp/templates/app/mcp_server_configs/sample_filesystem.json
viyv_mcp/templates/app/mcp_server_configs/sample_slack.json
viyv_mcp/templates/app/prompts/sample_prompt.py
viyv_mcp/templates/app/resources/sample_echo_resource.py
viyv_mcp/templates/app/tools/sample_math_tools.py
viyv_mcp-0.1.17.dist-info/licenses/LICENSE
viyv_mcp-0.1.17.dist-info/METADATA
viyv_mcp-0.1.17.dist-info/WHEEL
viyv_mcp-0.1.17.dist-info/entry_points.txt
viyv_mcp-0.1.17.dist-info/top_level.txt
viyv_mcp-0.1.17.dist-info/RECORD
