Metadata-Version: 2.4
Name: viyv_mcp
Version: 0.1.17
Summary: A simple wrapper library for FastMCP + Starlette
Author-email: hiroki takezawa <hiroki.takezawa@brainfiber.net>
License: MIT
Project-URL: Homepage, https://github.com/BrainFiber/viyv_mcp
Project-URL: Repository, https://github.com/BrainFiber/viyv_mcp
Keywords: mcp,fastmcp,starlette,uvicorn
Requires-Python: >=3.10
License-File: LICENSE
Requires-Dist: starlette>=0.25.0
Requires-Dist: fastmcp>=2.12.3
Requires-Dist: uvicorn>=0.22.0
Requires-Dist: fastapi>=0.115.12
Requires-Dist: build>=1.2.2.post1
Requires-Dist: pydantic>=2
Requires-Dist: slack-bolt>=1.23.0
Requires-Dist: aiohttp>=3.11.18
Requires-Dist: openai-agents>=0.0.13
Requires-Dist: pytest>=7.0
Dynamic: license-file
